{"cluster.sm/N=128": {"components": 1, "largest_component": 597012, "states": 597012, "uniformization": 51.518159999999995}, "cluster.sm/N=16": {"components": 1, "largest_component": 10132, "states": 10132, "uniformization": 51.06120000000001}, "cluster.sm/N=2": {"components": 1, "largest_component": 276, "states": 276, "uniformization": 51.00408}, "cluster.sm/N=256": {"components": 1, "largest_component": 2373652, "states": 2373652, "uniformization": 52.0404}, "cluster.sm/N=32": {"components": 1, "largest_component": 38676, "states": 38676, "uniformization": 51.126479999999994}, "cluster.sm/N=4": {"components": 1, "largest_component": 820, "states": 820, "uniformization": 51.01224}, "cluster.sm/N=512": {"components": 1, "largest_component": 9465876, "states": 9465876, "uniformization": "error"}, "cluster.sm/N=64": {"components": 1, "largest_component": 151060, "states": 151060, "uniformization": 51.257039999999996}, "cluster.sm/N=8": {"components": 1, "largest_component": 2772, "states": 2772, "uniformization": 51.028560000000006}}